csb_util/__init__.py
csb_util/__main__.py
csb_util/csb.py
csb_util/py.typed
csb_util-0.1.dist-info/LICENSE
csb_util-0.1.dist-info/METADATA
csb_util-0.1.dist-info/WHEEL
csb_util-0.1.dist-info/top_level.txt
csb_util-0.1.dist-info/RECORD
