Metadata-Version: 2.1
Name: csb_util
Version: 0.1
Summary: Utility for encoding and decoding csb files
Author: fieryhenry
License: GNU General Public License v3 or later (GPLv3+)
Project-URL: Homepage, https://github.com/fieryhenry/csb_util
Project-URL: Repository, https://github.com/fieryhenry/csb_util
Project-URL: Issues, https://github.com/fieryhenry/csb_util/issues
Project-URL: Changelog, https://github.com/fieryhenry/csb_util/blob/main/CHANGELOG.md
Classifier: Development Status :: 3 - Alpha
Classifier: Programming Language :: Python :: 3
Classifier: Programming Language :: Python :: 3.9
Classifier: License :: OSI Approved :: GNU General Public License v3 or later (GPLv3+)
Classifier: Operating System :: OS Independent
Requires-Python: >=3.9
License-File: LICENSE
Requires-Dist: argparse
